setup.py
parse_shebang.egg-info/PKG-INFO
parse_shebang.egg-info/SOURCES.txt
parse_shebang.egg-info/dependency_links.txt
parse_shebang.egg-info/requires.txt
parse_shebang.egg-info/top_level.txt
parse_shebang.egg-info/zip-safe
parseshebang/__init__.py
test/test_acceptance.py
test/test_parse_shebang.py